app/__init__.py
app/__main__.py
app/main.py
pydantictest-0.1.2.dist-info/METADATA
pydantictest-0.1.2.dist-info/WHEEL
pydantictest-0.1.2.dist-info/entry_points.txt
pydantictest-0.1.2.dist-info/RECORD
